kahn_topo_sort/__init__.py
kahn_topo_sort/main.py
topo_sort/__init__.py
topo_sort/main.py
kahn_topo_sort-0.2.7.dist-info/METADATA
kahn_topo_sort-0.2.7.dist-info/WHEEL
kahn_topo_sort-0.2.7.dist-info/top_level.txt
kahn_topo_sort-0.2.7.dist-info/RECORD
