Metadata-Version: 2.1
Name: kahn-topo-sort
Version: 0.2.7
